README.rst
setup.py
alicloudcli.egg-info/PKG-INFO
alicloudcli.egg-info/SOURCES.txt
alicloudcli.egg-info/dependency_links.txt
alicloudcli.egg-info/entry_points.txt
alicloudcli.egg-info/requires.txt
alicloudcli.egg-info/top_level.txt
aliyuncli/__init__.py
aliyuncli/alicloud_zsh_complete.sh
aliyuncli/aliyunCliConfiugre.py
aliyuncli/aliyunCliHelp.py
aliyuncli/aliyunCliMain.py
aliyuncli/aliyunCliParser.py
aliyuncli/aliyunCliUpgrade.py
aliyuncli/aliyunCompleter.py
aliyuncli/aliyunExtensionCliHandler.py
aliyuncli/aliyunOpenApiData.py
aliyuncli/aliyunSdkConfigure.py
aliyuncli/aliyun_completer.py
aliyuncli/aliyuncli.py
aliyuncli/cliError.py
aliyuncli/commandConfigure.py
aliyuncli/configure.py
aliyuncli/handleEndPoint.py
aliyuncli/paramOptimize.py
aliyuncli/response.py
aliyuncli/six.py
aliyuncli/table.py
aliyuncli/text.py
aliyuncli/advance/__init__.py
aliyuncli/advance/ecsExportHandler.py
aliyuncli/advance/ecsImportHandler.py
aliyuncli/advance/rdsExportHandler.py
aliyuncli/advance/rdsImportHandler.py
aliyuncli/advance/userConfigHandler.py
aliyuncli/advance/userProfileHandler.py
aliyuncli/ossadp/__init__.py
aliyuncli/ossadp/ossHandler.py