Metadata-Version: 1.0
Name: alicloudcli
Version: 1.0.2
Summary: Universal Command Line Environment for alicloud
Home-page: http://www.alicloud.com
Author: aliyun-developers-efficiency
Author-email: aliyun-developers-efficiency@list.alibaba-inc.com
License: UNKNOWN
Platform: unix
Platform: linux
Platform: osx
Platform: win64
Platform: win32
